{"version":20180619,"tag":"14085503","params":"widget\ndiaX","when_created":1665551014.3649,"parent_id":"35f7b123","props":[],"when_updated":1665576679.5992,"items":{"2":{"type":"branch","branchId":0,"one":"5","id":"2"},"3":{"type":"action","id":"3","one":"1","text":"return (diaX - widget.visuals.scrollX) *\nzoom"},"1":{"type":"end","id":"1"},"5":{"type":"action","text":"zoom = widget.zoom \/ 10000","one":"3","id":"5"}},"keywords":{"scenario":false,"async":false,"export":false,"function":true,"algoprop":false},"created_by":"stipan","updated_by":"stipan","type":"drakon","name":"diagramToWidgetX","language":"LANG_S42"}