{"version":20180619,"tag":"524951","params":"userTheme\nconfig","when_created":1657287494.2486,"parent_id":"befd80d4","props":[],"language":"LANG_S42","items":{"8":{"type":"action","id":"8","one":"12","text":"Object.assign(theme, userTheme)"},"1":{"type":"end","id":"1"},"9":{"type":"action","text":"theme = {\n    \"icons\": {},\n    \"background\": \"#97D3E1\",\n    \"color\": \"black\",\n    \"iconBack\": \"white\",\n    \"lines\": \"black\",\n    \"backText\": \"black\",\n    \"iconBorder\": \"black\",\n    \"candyFill\": \"#00ff00\",\n    \"handleFill\": \"#d0ff00\",\n    \"candyBorder\": \"black\",\n    \"valFill\": \"yellow\",\n    \"internalLine\": \"black\",\n    \"valBorder\": \"black\",\n    \"scrollBar\": \"rgba(0, 0, 0, 0.3)\",\n    \"scrollBarHover\": \"black\",\n    \"shadowColor\": \"\",\n    \"shadowBlur\": 6,\n    \"shadowOffsetX\": 0,\n    \"shadowOffsetY\": 0,\n    \"lineWidth\": 1,\n    \"borderWidth\": 1,\n    \"guides\": \"darkred\",\n    \"highlight\": \"magenta\",\n    \"commentBack\": \"#2293bb\"\n}","one":"8","id":"9"},"15":{"type":"action","id":"15","one":"16","text":"setIconDefaultProps(\n    theme.icons,\n    [\"header\"],\n    {font: config.headerFont}\n)"},"16":{"type":"action","text":"setIconDefaultProps(\n    theme.icons,\n    [\"branch\"],\n    {font: config.branchFont}\n)","one":"11","id":"16"},"11":{"branchId":3,"one":"13","id":"11","type":"branch","text":"Exit"},"12":{"branchId":2,"one":"14","id":"12","type":"branch","text":"Special icons"},"3":{"type":"action","text":"userTheme = userTheme || {}","one":"9","id":"3"},"2":{"branchId":1,"one":"3","id":"2","type":"branch","text":"Branch1"},"13":{"type":"action","text":"return theme","one":"1","id":"13"},"14":{"type":"action","text":"setIconDefaultProps(\n    theme.icons,\n    [\n        \"duration\",\n        \"ctrlstart\",\n        \"ctrlend\",\n        \"pause\",\n        \"timer\",\n        \"group-duration\"\n    ],\n    {iconBack: \"#fffdbd\"}\n)","one":"15","id":"14"}},"type":"drakon","when_updated":1673008535.7329,"updated_by":"stipan","keywords":{"scenario":false,"async":false,"export":false,"function":true,"algoprop":false},"name":"copyTheme","created_by":"stipan"}