{"version":20180619,"tag":"716701688","params":"ctx\nx\ny\nw\nh","when_created":1666762325.1165,"parent_id":"683f5bbe","props":[],"language":"LANG_S42","items":{"4":{"type":"action","text":"x0 = x - w\nx1 = x0 + radius\nx3 = x + w\nx2 = x3 - radius\ntop = y - h\nbottom = y + h","one":"3","id":"4"},"1":{"type":"end","id":"1"},"5":{"type":"action","text":"radius = h * 2","one":"4","id":"5"},"2":{"branchId":0,"one":"5","id":"2","type":"branch","text":""},"3":{"type":"action","id":"3","one":"1","text":"ctx.beginPath()\nctx.arc(\n    x1,\n    bottom,\n    radius,\n    Math.PI * 1.0,\n    Math.PI * 1.5\n)\nctx.lineTo(x2, top)\nctx.arc(\n    x2,\n    bottom,\n    radius,\n    Math.PI * 1.5,\n    Math.PI * 0.0\n)\nctx.closePath()"}},"keywords":{"scenario":false,"async":false,"export":false,"function":true,"algoprop":false},"type":"drakon","updated_by":"stipan","when_updated":1666762433.7241,"name":"buildCtrlStartPath","created_by":"stipan"}