{"keywords":{"scenario":false,"async":false,"export":false,"function":true,"algoprop":false},"tag":"498795388","params":"widget\nprim","when_created":1663767501.173,"parent_id":"b0881e64","props":[],"created_by":"stipan","items":{"8":{"type":"action","text":"change.fields.flag1 = 0","one":"12","id":"8"},"1":{"type":"end","id":"1"},"5":{"one":"7","id":"5","type":"action","text":"change = {\n    id: prim.id,\n    fields: {},\n    op: \"update\"\n}","two":""},"9":{"type":"action","id":"9","one":"12","text":"change.fields.flag1 = 1"},"6":{"type":"action","text":"node = getFree(widget.visuals, prim.id)","one":"5","id":"6"},"12":{"type":"action","id":"12","one":"13","text":"change.fields.loX = -node.loX\nchange.fields.hiX = -node.hiX"},"7":{"flag1":1,"id":"7","type":"question","text":"node.flag1","one":"8","two":"9"},"2":{"type":"branch","branchId":0,"one":"6","id":"2"},"13":{"type":"action","text":"return updateAndKeepSelection(\n    widget,\n    [change]\n)","one":"1","id":"13"}},"type":"drakon","language":"LANG_S42","updated_by":"stipan","version":20180619,"name":"flipGroup","when_updated":1671129179.5027}